ghunt/__init__.py
ghunt/apis/__init__.py
ghunt/apis/accounts.py
ghunt/apis/calendar.py
ghunt/apis/clientauthconfig.py
ghunt/apis/digitalassetslinks.py
ghunt/apis/drive.py
ghunt/apis/fireconsolepa.py
ghunt/apis/geolocation.py
ghunt/apis/identitytoolkit.py
ghunt/apis/mobilesdk.py
ghunt/apis/peoplepa.py
ghunt/apis/playgames.py
ghunt/apis/playgateway.py
ghunt/apis/vision.py
ghunt/cli.py
ghunt/config.py
ghunt/errors.py
ghunt/ghunt.py
ghunt/globals.py
ghunt/helpers/__init__.py
ghunt/helpers/auth.py
ghunt/helpers/banner.py
ghunt/helpers/calendar.py
ghunt/helpers/drive.py
ghunt/helpers/gcp.py
ghunt/helpers/gmail.py
ghunt/helpers/gmaps.py
ghunt/helpers/ia.py
ghunt/helpers/iam.py
ghunt/helpers/knowledge.py
ghunt/helpers/listener.py
ghunt/helpers/playgames.py
ghunt/helpers/playstore.py
ghunt/helpers/utils.py
ghunt/knowledge/__init__.py
ghunt/knowledge/drive.py
ghunt/knowledge/iam.py
ghunt/knowledge/keys.py
ghunt/knowledge/maps.py
ghunt/knowledge/people.py
ghunt/knowledge/services.py
ghunt/knowledge/sig.py
ghunt/lib/__init__.py
ghunt/lib/httpx.py
ghunt/modules/__init__.py
ghunt/modules/drive.py
ghunt/modules/email.py
ghunt/modules/gaia.py
ghunt/modules/geolocate.py
ghunt/modules/login.py
ghunt/modules/spiderdal.py
ghunt/objects/__init__.py
ghunt/objects/apis.py
ghunt/objects/base.py
ghunt/objects/encoders.py
ghunt/objects/session.py
ghunt/objects/utils.py
ghunt/parsers/__init__.py
ghunt/parsers/calendar.py
ghunt/parsers/clientauthconfig.py
ghunt/parsers/digitalassetslinks.py
ghunt/parsers/drive.py
ghunt/parsers/geolocate.py
ghunt/parsers/identitytoolkit.py
ghunt/parsers/mobilesdk.py
ghunt/parsers/people.py
ghunt/parsers/playgames.py
ghunt/parsers/playgateway.py
ghunt/parsers/vision.py
ghunt/protos/__init__.py
ghunt/protos/playgatewaypa/__init__.py
ghunt/protos/playgatewaypa/definitions/get_player.proto
ghunt/protos/playgatewaypa/definitions/get_player_response.proto
ghunt/protos/playgatewaypa/definitions/search_player.proto
ghunt-2.3.3.dist-info/entry_points.txt
ghunt-2.3.3.dist-info/LICENSE.md
ghunt-2.3.3.dist-info/METADATA
ghunt-2.3.3.dist-info/WHEEL
ghunt-2.3.3.dist-info/RECORD
