Metadata-Version: 2.1
Name: ghunt
Version: 2.3.3
Summary: An offensive Google framework.
License: AGPL-3.0
Author: mxrch
Author-email: mxrch.dev@pm.me
Requires-Python: >=3.11,<4.0
Classifier: License :: OSI Approved :: GNU Affero General Public License v3
Classifier: Programming Language :: Python :: 3
Classifier: Programming Language :: Python :: 3.11
Classifier: Programming Language :: Python :: 3.12
Requires-Dist: alive-progress (>=3.1.5,<4.0.0)
Requires-Dist: autoslot (>=2022.12.1,<2023.0.0)
Requires-Dist: beautifulsoup4 (>=4.12.3,<5.0.0)
Requires-Dist: beautifultable (>=1.1.0,<2.0.0)
Requires-Dist: dnspython (>=2.7.0,<3.0.0)
Requires-Dist: geopy (>=2.4.1,<3.0.0)
Requires-Dist: httpx[http2] (>=0.27.2,<0.28.0)
Requires-Dist: humanize (>=4.10.0,<5.0.0)
Requires-Dist: imagehash (>=4.3.1,<5.0.0)
Requires-Dist: inflection (>=0.5.1,<0.6.0)
Requires-Dist: jsonpickle (>=3.3.0,<4.0.0)
Requires-Dist: packaging (>=24.1,<25.0)
Requires-Dist: pillow (>=10.4.0,<11.0.0)
Requires-Dist: protobuf (>=5.28.2,<6.0.0)
Requires-Dist: python-dateutil (>=2.9.0.post0,<3.0.0)
Requires-Dist: rich (>=13.9.1,<14.0.0)
Requires-Dist: rich-argparse (>=1.5.2,<2.0.0)
